aws/__init__.py
aws/dynamodb/__init__.py
aws/dynamodb/dynamodb_repository.py
aws/dynamodb/dynamodbdao.py
dynamoplus/__init__.py
dynamoplus/dynamo_plus_v2.py
dynamoplus/models/__init__.py
dynamoplus/models/query/__init__.py
dynamoplus/models/query/conditions.py
dynamoplus/models/query/index.py
dynamoplus/models/system/__init__.py
dynamoplus/models/system/aggregation/__init__.py
dynamoplus/models/system/aggregation/aggregation.py
dynamoplus/models/system/client_authorization/__init__.py
dynamoplus/models/system/client_authorization/client_authorization.py
dynamoplus/models/system/collection/__init__.py
dynamoplus/models/system/collection/collection.py
dynamoplus/models/system/index/__init__.py
dynamoplus/models/system/index/index.py
dynamoplus/service/__init__.py
dynamoplus/service/indexing_decorator.py
dynamoplus/service/security/__init__.py
dynamoplus/service/security/security.py
dynamoplus/service/validation_service.py
dynamoplus/utils/__init__.py
dynamoplus/utils/decimalencoder.py
dynamoplus/utils/utils.py
dynamoplus/v2/__init__.py
dynamoplus/v2/admin.py
dynamoplus/v2/indexing_service_v2.py
dynamoplus/v2/repository/__init__.py
dynamoplus/v2/repository/domain_repository.py
dynamoplus/v2/repository/repositories.py
dynamoplus/v2/repository/repositories_v2.py
dynamoplus/v2/repository/system_repositories.py
dynamoplus/v2/service/__init__.py
dynamoplus/v2/service/common.py
dynamoplus/v2/service/domain/__init__.py
dynamoplus/v2/service/domain/domain_service_v2.py
dynamoplus/v2/service/query_service.py
dynamoplus/v2/service/query_service_v2.py
dynamoplus/v2/service/system/__init__.py
dynamoplus/v2/service/system/aggregation_service.py
dynamoplus/v2/service/system/aggregation_service_v2.py
dynamoplus/v2/service/system/system_service_v2.py
dynamoplus_core-0.5.5.dist-info/METADATA
dynamoplus_core-0.5.5.dist-info/WHEEL
dynamoplus_core-0.5.5.dist-info/RECORD
